charlagui/__init__.py
charlagui/__main__.py
charlagui/gui/__init__.py
charlagui/utils/__init__.py
charlagui/utils/parser.py
CharlaGUI-1.1.dist-info/LICENSE
CharlaGUI-1.1.dist-info/METADATA
CharlaGUI-1.1.dist-info/WHEEL
CharlaGUI-1.1.dist-info/entry_points.txt
CharlaGUI-1.1.dist-info/top_level.txt
CharlaGUI-1.1.dist-info/RECORD
