Metadata-Version: 2.1
Name: CharlaGUI
Version: 1.1
Summary: GUI for Charlatano and RatPoison CS:GO Cheat
Home-page: https://github.com/M4cs/CharlaGUI
Author: Max Bridgland
Author-email: mabridgland@protonmail.com
License: UNKNOWN
Keywords: csgo,steam,valve,charlatano,hack,gui. pysimplegui
Platform: UNKNOWN
Classifier: Programming Language :: Python :: 3
Classifier: Programming Language :: Python :: 3.4
Classifier: Programming Language :: Python :: 3.5
Classifier: Programming Language :: Python :: 3.6
Classifier: Programming Language :: Python :: 3.7
Classifier: Topic :: Multimedia :: Graphics
Classifier: Operating System :: OS Independent
Requires-Dist: PySimpleGUIQt (>=0.26.0)
Requires-Dist: PySide2 (>=5.13.0)
Requires-Dist: psutil (==5.6.2)
